websocket_server/__init__.py
websocket_server/thread.py
websocket_server/websocket_server.py
websocket_server-0.6.4.dist-info/LICENSE
websocket_server-0.6.4.dist-info/METADATA
websocket_server-0.6.4.dist-info/WHEEL
websocket_server-0.6.4.dist-info/top_level.txt
websocket_server-0.6.4.dist-info/RECORD
